gpu_benchmark/__init__.py
gpu_benchmark/database.py
gpu_benchmark/main.py
gpu_benchmark/benchmarks/__init__.py
gpu_benchmark/benchmarks/nanogpt_train.py
gpu_benchmark/benchmarks/qwen3_0_6b.py
gpu_benchmark/benchmarks/stable_diffusion_1_5.py
gpu_benchmark-0.4.3.dist-info/licenses/LICENSE
gpu_benchmark-0.4.3.dist-info/METADATA
gpu_benchmark-0.4.3.dist-info/WHEEL
gpu_benchmark-0.4.3.dist-info/entry_points.txt
gpu_benchmark-0.4.3.dist-info/top_level.txt
gpu_benchmark-0.4.3.dist-info/RECORD
