Metadata-Version: 2.4
Name: gpu_benchmark
Version: 0.4.3
Summary: GPU benchmarking tool for training and inference
Author-email: Roland Graser <roland@unitedcompute.ai>, Max Hager <maxhager28@gmail.com>
License-File: LICENSE
Requires-Dist: torch
Requires-Dist: tqdm
Requires-Dist: diffusers
Requires-Dist: transformers
Requires-Dist: accelerate
Requires-Dist: pynvml
Requires-Dist: supabase
Requires-Dist: tiktoken
Requires-Dist: requests
Dynamic: license-file
